rrdtool.cpython-35m-darwin.so
rrdtool-0.1.10.dist-info/DESCRIPTION.rst
rrdtool-0.1.10.dist-info/METADATA
rrdtool-0.1.10.dist-info/RECORD
rrdtool-0.1.10.dist-info/WHEEL
rrdtool-0.1.10.dist-info/metadata.json
rrdtool-0.1.10.dist-info/top_level.txt
